pyramid_useragent/__init__.py
pyramid_useragent/tests.py
pyramid_useragent-0.4.0.dist-info/LICENSE.txt
pyramid_useragent-0.4.0.dist-info/METADATA
pyramid_useragent-0.4.0.dist-info/WHEEL
pyramid_useragent-0.4.0.dist-info/top_level.txt
pyramid_useragent-0.4.0.dist-info/RECORD
