Metadata-Version: 2.1
Name: pyramid-useragent
Version: 0.4.0
Summary: HTTP User-Agent parser for Pyramid
Home-page: https://github.com/pior/pyramid_useragent
Author: Pior Bastida
Author-email: pior@pbastida.net
License: BSD-derived (http://www.repoze.org/LICENSE.txt)
Keywords: web wsgi pylons pyramid user-agent
Platform: UNKNOWN
Classifier: Intended Audience :: Developers
Classifier: Programming Language :: Python
Classifier: Programming Language :: Python :: 2
Classifier: Programming Language :: Python :: 2.7
Classifier: Programming Language :: Python :: 3
Classifier: Programming Language :: Python :: 3.6
Classifier: Programming Language :: Python :: 3.7
Classifier: Programming Language :: Python :: Implementation :: CPython
Classifier: Framework :: Pyramid
Provides-Extra: docs
Provides-Extra: dev
